jsonteng_contribs/__init__.py
jsonteng_contribs/tags/__init__.py
jsonteng_contribs/tags/ipv4_host_gateway_tag.py
jsonteng_contribs/tags/ipv4_host_ip_tag.py
jsonteng_contribs/tags/ipv4_host_netmask_tag.py
jsonteng_contribs/tags/ipv4_subnet_tag.py
jsonteng_contribs-1.0.8.dist-info/METADATA
jsonteng_contribs-1.0.8.dist-info/WHEEL
jsonteng_contribs-1.0.8.dist-info/top_level.txt
jsonteng_contribs-1.0.8.dist-info/RECORD
