Metadata-Version: 2.1
Name: jsonteng-contribs
Version: 1.0.8
Summary: Tag contributions.
Home-page: UNKNOWN
Author: VMware
Author-email: jimy@vmware.com
License: UNKNOWN
Platform: UNKNOWN
Classifier: Programming Language :: Python :: 3
Classifier: License :: OSI Approved :: Apache Software License
Classifier: Operating System :: OS Independent
